Workbook
Name aporte: Folha1!$D$17
Name qtd_anos: Folha1!$D$18
Name Rendimento_carteira: Folha1!$D$13
Name tx_mensal: Folha1!$D$19

Sheet Folha1
B11: CONFIGURAÇÕES
B12: Salário | D12: 2000
B13: Rendimento carteira | D13: 0.0108
B14: Sugestão de investimento (30%) | D14: =D12*30% -> 600
B16: INVESTIMENTO MENSAL
B17: Quanto investir por mês? | D17: 220
B18: Por quantos anos? | D18: 25
B19: Taxa de rendimento mensal? | D19: 0.01079
B20: Patrimonio acumulado? | D20: =FV(tx_mensal,qtd_anos*12,aporte*-1) -> 489742.37
B21: Dividendos mensais? | D21: =D20*D13 -> 5289.2176
B22: Tempo para acumular 1 milhão | D22: =INT(NPER(tx_mensal,aporte*-1,0,1000000)/12)&" anos" -> 30 anos
B24: CENÁRIOS | D24: DIVIDENDOS
A25: 2 | B25: Quanto em 2 anos? | C25: =FV($D$19,$A25*12,$D$17*-1) -> 5990.078 | D25: =C25*$D$13 -> 64.692842
A26: 5 | B26: Quanto em 5 anos? | C26: =FV($D$19,$A26*12,$D$17*-1) -> 18430.921 | D26: =C26*$D$13 -> 199.05395
A27: 10 | B27: Quanto em 10 anos? | C27: =FV($D$19,$A27*12,$D$17*-1) -> 53522.527 | D27: =C27*$D$13 -> 578.04329
A28: 20 | B28: Quanto em 20 anos? | C28: =FV($D$19,$A28*12,$D$17*-1) -> 247543.65 | D28: =C28*$D$13 -> 2673.4714
A29: 30 | B29: Quanto em 30 anos? | C29: =FV($D$19,$A29*12,$D$17*-1) -> 950877.32 | D29: =C29*$D$13 -> 10269.475
B32: PERFIL | C32: Moderado
C33: =VLOOKUP($C$32,Folha2!$H:$I,2,0) -> Equilíbrio entre renda e crescimento
B34: Valor a ser investido por mês | C34: =aporte -> 220
B36: TIPO DE FII | C36: Percentual sugerido | D36: Valores
B37: Papel | C37: =VLOOKUP($C$32&"-"&B37,Folha2!$A:$D,4,0) -> 0.3 | D37: =C37*$C$34 -> 66
B38: Tijolo | C38: =VLOOKUP($C$32&"-"&B38,Folha2!$A:$D,4,0) -> 0.3 | D38: =C38*$C$34 -> 66
B39: Híbrido | C39: =VLOOKUP($C$32&"-"&B39,Folha2!$A:$D,4,0) -> 0.15 | D39: =C39*$C$34 -> 33
B40: FOFs | C40: =VLOOKUP($C$32&"-"&B40,Folha2!$A:$D,4,0) -> 0.15 | D40: =C40*$C$34 -> 33
B41: Desenvolvimento | C41: =VLOOKUP($C$32&"-"&B41,Folha2!$A:$D,4,0) -> 0.05 | D41: =C41*$C$34 -> 11
B42: Hotelaria | C42: =VLOOKUP($C$32&"-"&B42,Folha2!$A:$D,4,0) -> 0.05 | D42: =C42*$C$34 -> 11
D43: =SUM(D37:D42) -> 220

Sheet Folha2
A2: Chave | B2: PERFIL | C2: TIPO DE FII | D2: Percent | H2: PERFIL | I2: Caract
A3: =B3&"-"&C3 -> Conservador-Papel | B3: Conservador | C3: Papel | D3: 0.4 | H3: Conservador | I3: Renda estável, baixo risco, previsibilidade
A4: =B4&"-"&C4 -> Conservador-Tijolo | B4: Conservador | C4: Tijolo | D4: 0.35 | H4: Moderado | I4: Equilíbrio entre renda e crescimento
A5: =B5&"-"&C5 -> Conservador-Híbrido | B5: Conservador | C5: Híbrido | D5: 0.15 | H5: Agressivo | I5: Alto crescimento, maior risco, volatilidade
A6: =B6&"-"&C6 -> Conservador-FOFs | B6: Conservador | C6: FOFs | D6: 0.1
A7: =B7&"-"&C7 -> Conservador-Desenvolvimento | B7: Conservador | C7: Desenvolvimento | D7: 0
A8: =B8&"-"&C8 -> Conservador-Hotelaria | B8: Conservador | C8: Hotelaria | D8: 0
A9: =B9&"-"&C9 -> Moderado-Papel | B9: Moderado | C9: Papel | D9: 0.3
A10: =B10&"-"&C10 -> Moderado-Tijolo | B10: Moderado | C10: Tijolo | D10: 0.3
A11: =B11&"-"&C11 -> Moderado-Híbrido | B11: Moderado | C11: Híbrido | D11: 0.15
A12: =B12&"-"&C12 -> Moderado-FOFs | B12: Moderado | C12: FOFs | D12: 0.15
A13: =B13&"-"&C13 -> Moderado-Desenvolvimento | B13: Moderado | C13: Desenvolvimento | D13: 0.05
A14: =B14&"-"&C14 -> Moderado-Hotelaria | B14: Moderado | C14: Hotelaria | D14: 0.05
A15: =B15&"-"&C15 -> Agressivo-Papel | B15: Agressivo | C15: Papel | D15: 0.2
A16: =B16&"-"&C16 -> Agressivo-Tijolo | B16: Agressivo | C16: Tijolo | D16: 0.25
A17: =B17&"-"&C17 -> Agressivo-Híbrido | B17: Agressivo | C17: Híbrido | D17: 0.15
... A20: =B20&"-"&C20 -> Agressivo-Hotelaria | B20: Agressivo | C20: Hotelaria | D20: 0.15
